akgoodreads/__init__.py
akgoodreads/credentials.py
akgoodreads/definitions.py
akgoodreads/gr_parser.py
akgoodreads/log.py
akgoodreads/main.py
akgoodreads-0.0.3.dist-info/LICENSE
akgoodreads-0.0.3.dist-info/WHEEL
akgoodreads-0.0.3.dist-info/METADATA
akgoodreads-0.0.3.dist-info/RECORD
