Metadata-Version: 2.1
Name: akgoodreads
Version: 0.0.3
Summary: Goodreads python wrapper
Author-email: Arun Kishore <goodreads@rpakishore.co.in>
Requires-Python: >=3.5
Classifier: License :: OSI Approved :: MIT License
Requires-Dist: requests>=2.28.2
Requires-Dist: xmltodict>=0.13.0
Requires-Dist: pytest>=7.2.1
Requires-Dist: keyring>=23.13.1
Requires-Dist: rich>=13.3.1
Project-URL: Home, https://github.com/rpakishore/goodreads
